{
    "timestamp": "2026-07-07T16:19:25.887374",
    "ticker": "AAPL",
    "question": "Invest in Apple?",
    "company_info": {
        "company_name": "Apple Inc.",
        "sector": "Technology",
        "industry": "Consumer Electronics",
        "market_cap": 4612196663296,
        "currency": "USD",
        "country": "United States"
    },
    "market_cap": 4612196663296,
    "beta": 1.2,
    "sentiment": {
        "label": "neutral",
        "score": 0.8118128776550293
    },
    "retrieved_chunks": [
        {
            "text": "Enterprise deployment of Apple silicon accelerated globally, especially among software development and AI engineering teams.",
            "metadata": {
                "speaker": "CEO",
                "company": "",
                "importance": 0.6,
                "quarter": "",
                "section": "AI"
            }
        },
        {
            "text": "Enterprise customers increasingly adopted Apple silicon infrastructure for machine learning and creative workloads.",
            "metadata": {
                "section": "AI",
                "quarter": "",
                "importance": 0.55,
                "company": "",
                "speaker": "CEO"
            }
        },
        {
            "text": "Welcome to Apple’s Q2 earnings conference call.",
            "metadata": {
                "importance": 0.5,
                "speaker": "Operator",
                "quarter": "",
                "company": "",
                "section": "General Discussion"
            }
        }
    ],
    "generated_answer": " The provided data does not offer sufficient insights into the current state or future prospects of Apple Inc., making an investment recommendation based solely on these details challenging. While revenue growth has been steady at around 6%, profitability indicators like operating margin (31.97%) suggest strong performance but free cash flow (-9.23% growth) indicates that liquidity might become strained over time. Additionally, leverage ratios remain relatively high at 1.34, which could pose challenges if interest rates rise significantly. Despite positive sentiment expressed by executives regarding their technology advancements such as Apple Silicon deployments across various industries including software development and artificial intelligence, there's no clear indication about how well these technologies will translate into long-term competitive advantages or market penetration figures. Therefore, while short-term stability seems assured due to robust demand for new hardware models driven primarily by consumer electronics trends, investors should exercise caution given potential vulnerabilities related to operational efficiency and capital allocation decisions made post-pandemic recovery phases where cost-cutting measures were likely implemented aggressively to maintain profit margins amidst supply chain disruptions and inflationary pressures. \n\nPlease provide more specific industry analysis, historical sales numbers, detailed balance sheet items, recent product launches, competitor comparisons, etc. These would help paint a clearer picture of what",
    "context.valuation_results": {
        "enterprise_value": 1289939357697.8591,
        "equity_value": 1227216357697.8591,
        "fcff_forecasts": {
            "forecast_fcff": {
                "Year_1": 107445713279.18184,
                "Year_2": 109393205237.2034,
                "Year_3": 111375996183.06548,
                "Year_4": 113394725923.5398,
                "Year_5": 115450045862.12445
            }
        },
        "wacc": 0.11015047578161057,
        "sensitivity_analysis": {
            "8%": {
                "1%": 1628548439094.0,
                "2%": 1644672681065.0,
                "3%": 1660796923036.0,
                "4%": 1676921165007.0,
                "5%": 1693045406978.0
            },
            "9%": {
                "1%": 1447598612528.0,
                "2%": 1461931272058.0,
                "3%": 1476263931588.0,
                "4%": 1490596591118.0,
                "5%": 1504929250648.0
            },
            "10%": {
                "1%": 1302838751275.0,
                "2%": 1315738144852.0,
                "3%": 1328637538429.0,
                "4%": 1341536932006.0,
                "5%": 1354436325583.0
            },
            "11%": {
                "1%": 1184398864795.0,
                "2%": 1196125586229.0,
                "3%": 1207852307663.0,
                "4%": 1219579029096.0,
                "5%": 1231305750530.0
            },
            "12%": {
                "1%": 1085698959396.0,
                "2%": 1096448454043.0,
                "3%": 1107197948691.0,
                "4%": 1117947443338.0,
                "5%": 1128696937986.0
            }
        }
    },
    "investment_thesis": {},
    "evaluation": " The provided data does not offer sufficient insights into the current state or future prospects of Apple Inc., making an investment recommendation based solely on these details challenging. While revenue growth has been steady at around 6%, profitability indicators like operating margin (31.97%) suggest strong performance but free cash flow (-9.23% growth) indicates that liquidity might become strained over time. Additionally, leverage ratios remain relatively high at 1.34, which could pose challenges if interest rates rise significantly. Despite positive sentiment expressed by executives regarding their technology advancements such as Apple Silicon deployments across various industries including software development and artificial intelligence, there's no clear indication about how well these technologies will translate into long-term competitive advantages or market penetration figures. Therefore, while short-term stability seems assured due to robust demand for new hardware models driven primarily by consumer electronics trends, investors should exercise caution given potential vulnerabilities related to operational efficiency and capital allocation decisions made post-pandemic recovery phases where cost-cutting measures were likely implemented aggressively to maintain profit margins amidst supply chain disruptions and inflationary pressures. \n\nPlease provide more specific industry analysis, historical sales numbers, detailed balance sheet items, recent product launches, competitor comparisons, etc. These would help paint a clearer picture of what",
    "metadata": {}
}